pulumi_awsx/__init__.py
pulumi_awsx/_utilities.py
pulumi_awsx/provider.py
pulumi_awsx/pulumi-plugin.json
pulumi_awsx/py.typed
pulumi_awsx/awsx/__init__.py
pulumi_awsx/awsx/_inputs.py
pulumi_awsx/cloudtrail/__init__.py
pulumi_awsx/cloudtrail/trail.py
pulumi_awsx/ec2/__init__.py
pulumi_awsx/ec2/_enums.py
pulumi_awsx/ec2/_inputs.py
pulumi_awsx/ec2/default_vpc.py
pulumi_awsx/ec2/get_default_vpc.py
pulumi_awsx/ec2/outputs.py
pulumi_awsx/ec2/vpc.py
pulumi_awsx/ecr/__init__.py
pulumi_awsx/ecr/_enums.py
pulumi_awsx/ecr/_inputs.py
pulumi_awsx/ecr/image.py
pulumi_awsx/ecr/registry_image.py
pulumi_awsx/ecr/repository.py
pulumi_awsx/ecs/__init__.py
pulumi_awsx/ecs/_enums.py
pulumi_awsx/ecs/_inputs.py
pulumi_awsx/ecs/ec2_service.py
pulumi_awsx/ecs/ec2_task_definition.py
pulumi_awsx/ecs/fargate_service.py
pulumi_awsx/ecs/fargate_task_definition.py
pulumi_awsx/lb/__init__.py
pulumi_awsx/lb/_inputs.py
pulumi_awsx/lb/application_load_balancer.py
pulumi_awsx/lb/network_load_balancer.py
pulumi_awsx/lb/target_group_attachment.py
pulumi_awsx-3.1.0.dist-info/METADATA
pulumi_awsx-3.1.0.dist-info/WHEEL
pulumi_awsx-3.1.0.dist-info/top_level.txt
pulumi_awsx-3.1.0.dist-info/RECORD
